setup.py
Husky/__init__.py
Husky/class_husky.py
Husky/dict_husky.py
Husky/function_husky.py
Husky/generator_husky.py
Husky/instance_husky.py
Husky/iterable_husky.py
Husky/module_husky.py
Husky/type_husky.py
Husky/wrap.py
Husky.egg-info/PKG-INFO
Husky.egg-info/SOURCES.txt
Husky.egg-info/dependency_links.txt
Husky.egg-info/top_level.txt