Metadata-Version: 1.0
Name: Husky
Version: 0.1.6
Summary: An advanced serializing library like pickle but can seralize more, like functions.
Home-page: https://github.com/Tefx/Husky
Author: Zhu Zhaomeng
Author-email: zhaomeng.zhu@gmail.com
License: UNKNOWN
Platform: UNKNOWN
Classifier: Development Status :: 4 - Beta
Classifier: License :: OSI Approved :: GNU Library or Lesser General Public License (LGPL)
